CPACqc/__init__.py
CPACqc/core/QCPipeline.py
CPACqc/core/__init__.py
CPACqc/core/config.py
CPACqc/core/entity.py
CPACqc/core/logger.py
CPACqc/core/utils.py
CPACqc/core/validation.py
CPACqc/services/__init__.py
CPACqc/services/logging_service.py
CPACqc/services/multiprocessing_service.py
CPACqc/services/plotting_service.py
CPACqc/services/report_generator_service.py
CPACqc/services/tabler_service.py
CPACqc/tests/core/test_validation.py
CPACqc/tests/service/test_multiprocessing.py
CPACqc/tests/ui/test_cli.py
CPACqc/ui/__init__.py
CPACqc/ui/cli.py
CPACqc/utils/__init__.py
CPACqc/utils/logging/__init__.py
CPACqc/utils/logging/log.py
CPACqc/utils/multiprocessing/__init__.py
CPACqc/utils/multiprocessing/multiprocessing_utils.py
CPACqc/utils/overlay/overlay.csv
CPACqc/utils/plotting/__init__.py
CPACqc/utils/plotting/nii_plotter.py
CPACqc/utils/plotting/plot.py
CPACqc/utils/report/__init__.py
CPACqc/utils/report/pdf.py
CPACqc/utils/tabler/__init__.py
CPACqc/utils/tabler/bids2table.py
CPACqc/utils/templates/index.html
CPACqc/utils/templates/script.js
README.md
cpacqc-0.2.18.dist-info/METADATA
cpacqc-0.2.18.dist-info/WHEEL
cpacqc-0.2.18.dist-info/entry_points.txt
static/cpac-qc_pdf.png
static/overlay.csv
static/sub-A00040524_ses-NFB3_qc_report.pdf
cpacqc-0.2.18.dist-info/RECORD
